definit_db_md/__init__.py
definit_db_md/config.py
definit_db_md/data/field/computer_science/description.md
definit_db_md/data/field/computer_science/index.md
definit_db_md/data/field/computer_science/definitions/data_structure/abstract_data_type.md
definit_db_md/data/field/computer_science/definitions/data_structure/bit_field.md
definit_db_md/data/field/computer_science/definitions/data_structure/collection.md
definit_db_md/data/field/computer_science/definitions/data_structure/map.md
definit_db_md/data/field/computer_science/definitions/data_structure/primitive_data_type.md
definit_db_md/data/field/computer_science/definitions/data_structure/collection/associative_array.md
definit_db_md/data/field/computer_science/definitions/data_structure/collection/bag.md
definit_db_md/data/field/computer_science/definitions/data_structure/collection/hash_table.md
definit_db_md/data/field/computer_science/definitions/data_structure/collection/heap_tree.md
definit_db_md/data/field/computer_science/definitions/data_structure/collection/priority_queue.md
definit_db_md/data/field/computer_science/definitions/data_structure/collection/queue.md
definit_db_md/data/field/computer_science/definitions/data_structure/collection/set.md
definit_db_md/data/field/computer_science/definitions/data_structure/collection/stack.md
definit_db_md/data/field/computer_science/definitions/data_structure/collection/trie.md
definit_db_md/data/field/computer_science/definitions/data_structure/collection/list/array.md
definit_db_md/data/field/computer_science/definitions/data_structure/collection/list/linked_list.md
definit_db_md/data/field/computer_science/definitions/data_structure/collection/list/list.md
definit_db_md/data/field/computer_science/definitions/data_structure/collection/string/ascii.md
definit_db_md/data/field/computer_science/definitions/data_structure/collection/string/character_encoding.md
definit_db_md-0.5.0.dist-info/METADATA
definit_db_md-0.5.0.dist-info/WHEEL
definit_db_md-0.5.0.dist-info/top_level.txt
definit_db_md-0.5.0.dist-info/RECORD
