Metadata-Version: 2.4
Name: definit-db-md
Version: 0.5.0
Summary: DefinIT Markdown database
Requires-Python: >=3.12
